{
  "uid" : "ab17fc5a4eb3bca4b216b548c7f9fcbc",
  "children" : [ {
    "name" : "B-22GNQ05P-1821.local",
    "children" : [ {
      "name" : "7103-MainThread",
      "children" : [ {
        "name" : "测试一下",
        "uid" : "261133bdf505aa0",
        "parentUid" : "e14dad13d871dd5efd911ea9ce2e9a06",
        "status" : "failed",
        "time" : {
          "start" : 1673009469407,
          "stop" : 1673009469789,
          "duration" : 382
        },
        "flaky" : false,
        "parameters" : [ "['测试一下', 'https://p10496-hk-bbs.ejoy.com/api/bbs/S3G二周年两行情书/index?count=100', 'get', '1、正确输入接口地址 2、正确输入请求参数 3、查看响应body是否正确', '3e4547b4bb12e9047950252d64b63472']" ]
      } ],
      "uid" : "e14dad13d871dd5efd911ea9ce2e9a06"
    } ],
    "uid" : "b2b2546d5aa4c3f2ef5095f1166eab94"
  } ],
  "name" : "timeline"
}